{
  "uid": "15",
  "name": "김희정",
  "enName": "Heejung Kim",
  "email": "kim2141hj@naver.com",
  "instagram": "@dau.ru",
  "projects": [
    {
      "uid": "27",
      "title": "LIMU' Brand identity",
      "category": "영상",
      "authors": [
        {
          "name": "김희정",
          "email": "kim2141hj@naver.com"
        }
      ],
      "project_image": "./15/project-1.png"
    },
    {
      "uid": "28",
      "title": "Ghostmates",
      "category": "브랜딩",
      "authors": [
        {
          "name": "김희정",
          "email": "kim2141hj@naver.com"
        }
      ],
      "project_image": "./15/project-2.png"
    }
  ]
}
